DiscordTranscript/__init__.py
DiscordTranscript/chat_exporter.py
DiscordTranscript/i18n.py
DiscordTranscript/construct/__init__.py
DiscordTranscript/construct/attachment_handler.py
DiscordTranscript/construct/message.py
DiscordTranscript/construct/transcript.py
DiscordTranscript/construct/assets/__init__.py
DiscordTranscript/construct/assets/attachment.py
DiscordTranscript/construct/assets/component.py
DiscordTranscript/construct/assets/embed.py
DiscordTranscript/construct/assets/reaction.py
DiscordTranscript/ext/__init__.py
DiscordTranscript/ext/cache.py
DiscordTranscript/ext/discord_import.py
DiscordTranscript/ext/discord_utils.py
DiscordTranscript/ext/discriminator.py
DiscordTranscript/ext/emoji_convert.py
DiscordTranscript/ext/html_generator.py
DiscordTranscript/html/__init__.py
DiscordTranscript/html/base.html
DiscordTranscript/html/attachment/audio.html
DiscordTranscript/html/attachment/image.html
DiscordTranscript/html/attachment/message.html
DiscordTranscript/html/attachment/video.html
DiscordTranscript/html/component/component_button.html
DiscordTranscript/html/component/component_container.html
DiscordTranscript/html/component/component_menu.html
DiscordTranscript/html/component/component_menu_options.html
DiscordTranscript/html/component/component_menu_options_emoji.html
DiscordTranscript/html/component/component_section.html
DiscordTranscript/html/component/component_separator.html
DiscordTranscript/html/component/component_text_display.html
DiscordTranscript/html/component/component_thumbnail.html
DiscordTranscript/html/embed/author.html
DiscordTranscript/html/embed/author_icon.html
DiscordTranscript/html/embed/body.html
DiscordTranscript/html/embed/body_image_only.html
DiscordTranscript/html/embed/description.html
DiscordTranscript/html/embed/field-inline.html
DiscordTranscript/html/embed/field.html
DiscordTranscript/html/embed/footer.html
DiscordTranscript/html/embed/footer_image.html
DiscordTranscript/html/embed/image.html
discordtranscript-1.3.1.dist-info/METADATA
discordtranscript-1.3.1.dist-info/WHEEL
discordtranscript-1.3.1.dist-info/top_level.txt
discordtranscript-1.3.1.dist-info/RECORD
