Metadata-Version: 2.4
Name: DiscordTranscript
Version: 1.3.1
Summary: A Discord chat exporter that is easy to use and customizable. // Un exporteur de chat Discord facile à utiliser et personnalisable.
Author-email: Xougui <xougui.7@gmail.com>
License-Expression: GPL-3.0-only
Project-URL: Source Code (GitHub), https://github.com/Xougui/DiscordTranscript
Keywords: archive,backup,channel-exporter,chat,chat-archive,chat exporter,chat-logs,discord,discord-api,discord-archive,discord-backup,discord-bot,discord-channel,discord-channel-exporter,discord-channel-history,discord-channel-logs,discord-chat,discord chat exporter,discord-export,discord-history,discord-html,discord-logs,discord-message-export,discord-messages,discord-transcript,discordpy,disnake,export,export-chat,export-discord,file,html,html-generator,html transcript,logs,message-archive,ne
Classifier: Operating System :: OS Independent
Classifier: Intended Audience :: Developers
Classifier: Natural Language :: French
Classifier: Programming Language :: Python :: 3.6
Classifier: Programming Language :: Python :: 3.7
Classifier: Programming Language :: Python :: 3.8
Classifier: Programming Language :: Python :: 3.9
Classifier: Programming Language :: Python :: 3.10
Classifier: Programming Language :: Python :: 3.11
Classifier: Programming Language :: Python :: 3.12
Classifier: Programming Language :: Python :: 3.13
Classifier: Topic :: Internet
Classifier: Topic :: Software Development :: Libraries
Classifier: Topic :: Software Development :: Libraries :: Python Modules
Classifier: Topic :: Utilities
Classifier: Typing :: Typed
Requires-Python: >=3.6
Requires-Dist: aiohttp
Requires-Dist: pytz
Requires-Dist: grapheme
Requires-Dist: emoji
Requires-Dist: discord.py
